oneliner.py
OLG4P-0.2.dist-info/LICENSE
OLG4P-0.2.dist-info/METADATA
OLG4P-0.2.dist-info/WHEEL
OLG4P-0.2.dist-info/top_level.txt
OLG4P-0.2.dist-info/RECORD
