Metadata-Version: 2.1
Name: OLG4P
Version: 0.2
Summary: Convert python script into python one-liner
Home-page: https://github.com/yunline/OLG4P
Author: yunline
License: MIT
License-File: LICENSE
